[
    {"text": "If you take too long to hit me back"},
    {"text": "I can't promise you how I'll react"},
    {"text": "But all I can say"},
    {"text": "Is at least I'll wait for you"},
    {"text": ""},
    {"text": "Lately, I've been on a roller-coaster"},
    {"text": "Tryna get a hold of my emotions"},
    {"text": "But all that I know"},
    {"text": "Is I need you close"},
    {"text": ""},
    {"text": "And I'ma scream and shout for what I love"},
    {"text": "Passionate, but I don't give no fucks"},
    {"text": "I admit that I'm a lil' messed up"},
    {"text": "But I can hide it when I'm all dressed up"},
    {"text": ""},
    {"text": "I'm obsessive and I love too hard"},
    {"text": "Good at overthinking with my heart"},
    {"text": "How you even think it got this far?"},
    {"text": "This far"},
    {"text": ""},
    {"text": "And I can be needy, way too damn needy"},
    {"text": "I can be needy, tell me how good it feels to be needed"},
    {"text": "I can be needy, so hard to please me"},
    {"text": "I know it feels so good to be needed"},
    {"text": ""},
    {"text": "Sorry if I'm up and down a lot (Yeah)"},
    {"text": "Sorry that I think I'm not enough"},
    {"text": "And sorry if I say sorry way too much"},
    {"text": ""},
    {"text": "You can go ahead and call me selfish (Selfish)"},
    {"text": "But after all this damage, I can't help it (Help it, yeah)"},
    {"text": "But what you can trust is I need your touch"},
    {"text": ""},
    {"text": "I'ma scream and shout for what I love"},
    {"text": "Passionate, but I don't give no fucks"},
    {"text": "I admit that I'm a lil' messed up"},
    {"text": "But I can hide it when I'm all dressed up"},
    {"text": ""},
    {"text": "I'm obsessive and I love too hard"},
    {"text": "Good at overthinking with my heart"},
    {"text": "How you even think it got this far?"},
    {"text": "This far"},
    {"text": ""},
    {"text": "And I can be needy, way too damn needy"},
    {"text": "I can be needy, tell me how good it feels to be needed"},
    {"text": "I can be needy, so hard to please me"},
    {"text": "I know it feels so good to be needed"},
    {"text": ""},
    {"text": "(Hmm, oh-ah)"},
    {"text": "(Oh-ah)"},
    {"text": ""}
]