[
    {"text": "Jogeuman nalgaetjit neol hyanghan ikkeullim"},
    {"text": "Nayege ttaraora sonjjitan geot gataseo"},
    {"text": "Aejeolhan nunppitgwa mueone iyagi"},
    {"text": "Gaseume hweoriga morachideon geunal bam"},
    {"text": ""},
    {"text": "Omyohan geudaeye moseube neokseul noko"},
    {"text": "Hanappunin yeonghoneul ppaetgigo"},
    {"text": "Geudaeye momjjise wanjeonhi chwihaeseo"},
    {"text": "Sum shwineun geotjocha ijeobeorin nainde"},
    {"text": ""},
    {"text": "Walcheucheoreom sappunhi anja"},
    {"text": "Nuneul ttel su eopseo"},
    {"text": "Shiseoni jayeonseure georeummada"},
    {"text": "Neol ttaragajana"},
    {"text": ""},
    {"text": "Nal annaehae jweo"},
    {"text": "Yeah geudaega salgo inneun gose"},
    {"text": "Nado hamkke deryeoga jweo"},
    {"text": "Oh sesange kkeuchirado dwittaragal teni"},
    {"text": "Budi nae shiyaeseo beoseonaji mara jweo"},
    {"text": "Achimi wado sarajiji mara jweo oh"},
    {"text": "Kkumeul kkuneun georeum"},
    {"text": "Geudaen namane areumdaun nabi"},
    {"text": ""},
    {"text": "Oh woo whoo whoo oh yeah yeah"},
    {"text": "Woo whoo whoo yeah"},
    {"text": "Woo whoo whoo listen"},
    {"text": ""},
    {"text": "Eodiseo wanneunji eodiro ganeunji"},
    {"text": "Chinjeolhi yeogikkaji majungeul wa jun neo"},
    {"text": "Gapareun oreumak kkakkajin jeolbyeokdo"},
    {"text": "Geokjeong ma mueotto duryeoul kkeoshi eopseuni"},
    {"text": ""},
    {"text": "Neoneun ppomnae uahan jatae"},
    {"text": "Oh nan myeot beonigo banhago"},
    {"text": "Sarangeun ireoke nado moreuge"},
    {"text": "Yegodo eopshi bulshie chajawa"},
    {"text": ""},
    {"text": "Walcheucheoreom sappunhi anja"},
    {"text": "Nuneul ttel su eopseo"},
    {"text": "Shiseoni jayeonseure georeummada"},
    {"text": "Neol ttaragajana oh no"},
    {"text": ""},
    {"text": "Nal annaehae jweo"},
    {"text": "Yeah geudaega salgo inneun gose"},
    {"text": "Nado hamkke deryeoga jweo"},
    {"text": "Oh sesange kkeuchirado dwittaragal teni"},
    {"text": "Budi nae shiyaeseo beoseonaji mara jweo"},
    {"text": "Achimi wado sarajiji mara jweo oh"},
    {"text": "Kkumeul kkuneun georeum"},
    {"text": "Geudaen namane areumdaun nabi"},
    {"text": ""},
    {"text": "Nasseon goseul hemaenda haedo"},
    {"text": "Gireul ireobeorindaedo"},
    {"text": "Nuguboda soljjikan"},
    {"text": "Naye mameul ttareul kkeoya"},
    {"text": "Joyonghi nune ttineun momjjit"},
    {"text": "Ganghago budeureoun nunppit"},
    {"text": "Geobuhal su eomneun nanikka yeah"},
    {"text": ""},
    {"text": "Nal deryeoga jweo"},
    {"text": "Yeah geudaega salgo inneun gose"},
    {"text": "Nado hamkke deryeoga jweo"},
    {"text": "Oh sesange kkeuchirado ttaragalkke oh no"},
    {"text": "Nae shiyaeseo beoseonaji mara jweo"},
    {"text": "Achimi wado sarajiji mara jweo oh"},
    {"text": "Jogeumahan sonjjit"},
    {"text": "Naye gaseumen hweoriga chinda"},
    {"text": ""},
    {"text": "Woo whoo whoo (Oh yeah yeah)"},
    {"text": "Woo whoo whoo (Oh yeah yeah)"},
    {"text": "Woo whoo whoo"},
    {"text": ""}
]