[
    {"text": "Ain't no magic tool to fix it","time": 0.4},
    {"text": "You should keep your distance","time": 3},
    {"text": "I'm only tellin' you because I care","time": 6},
    {"text": "'Cause I'm hard to love, find it hard to trust","time": 8.6},
    {"text": "When it feels too good, I just fuck it up","time": 14.3},
    {"text": "You want all of me, I can't give that much","time": 18.6},
    {"text": "So don't fall too hard 'cause I'm hard to love","time": 23.1},
    {"text": "(Yeah)","time": 32.5},
    {"text": "I'm hard to love","time": 35},
    {"text": "Yeah","time": 40.12},
    {"text": "(Hard to love)","time": 44},
    {"text": "Never meant to cause you a problem","time": 46.3},
    {"text": "Here I am yet once again with the same old story","time": 50.3},
    {"text": "You don't see the issues, I got 'em","time": 55.99},
    {"text": "Yeah, I do (Yeah, I do), yeah, it's true (Yeah, it's true)","time": 59.8},
    {"text": "I'll make it feel like heaven, but I swear I'm not a saint","time": 65},
    {"text": "And you won't see the truth 'caus? I'll be kissin' it away","time": 69},
    {"text": "Yeah, I'll be all you need until I'm drivin' you insan?","time": 73.99},
    {"text": "Baby, all I'm tryna do is save you the pain","time": 78.3},
    {"text": "'Cause I'm hard to love, find it hard to trust","time": 82},
    {"text": "When it feels too good, I just fuck it up","time": 87.23},
    {"text": "You want all of me, I can't give that much","time": 92},
    {"text": "So don't fall too hard 'cause I'm hard to love","time": 96.5},
    {"text": "(Yeah)","time": 104},
    {"text": "I'm hard to love","time": 108},
    {"text": "Yeah","time": 112},
    {"text": "(Hard to love)","time": 117},
    {"text": "Up 'til I'm down","time": 119.3},
    {"text": "I'm all in 'til I'm out","time": 121.25},
    {"text": "Got a lot to work out","time": 123.9},
    {"text": "'Til it's all behind me","time": 126},
    {"text": "You know you don't","time": 128.3},
    {"text": "Play with fire in the dark","time": 129.4},
    {"text": "Protect your heart","time": 131},
    {"text": "Ain't no goin' back once you start","time": 134},
    {"text": "I'm tryna be nice","time": 137},
    {"text": "(Yeah)","time": 141.3},
    {"text": "I'm hard to love","time": 144.89},
    {"text": "Yeah","time": 150},
    {"text": "(Hard to love)","time": 153},
    {"text": "","time": 157.6},
    {"text": "","time": 158}
]