[
    {"text": "aesseoseo hwaljjak useotteon nare","time": 0.1},
    {"text": "bameun wae deo eodulkka","time": 3},
    {"text": "It keeps bringing me down down down","time": 5},
    {"text": "modu neomu shwipge naebaetteon mal","time": 13},
    {"text": "ama deulligetji meojiana","time": 16},
    {"text": "I've heard enough I've heard enough","time": 18},
    {"text": "Of the things that I'm not ","time": 21},
    {"text": "on sesangi bakkwieogado","time": 25},
    {"text": "ajik naneun geudaeron geol","time": 30},
    {"text": "naega georeoganeun","time": 35},
    {"text": "i gireul kkumkkudeon","time": 37},
    {"text": "geuttae geudaero (2x)","time": 40},
    {"text": "nae maeireul chumchudeon","time": 42.8},
    {"text": "cheoeum geu jarie nama inneun geol","time": 46},
    {"text": "But you'll never know","time": 50},
    {"text": "Unless you walk in my shoes","time": 51},
    {"text": "You'll never know","time": 53},
    {"text": "eongkyeobeorin nae kkeun","time": 59},
    {"text": "'Cause everybody sees","time": 61},
    {"text": "What they wanna see","time": 62},
    {"text": "It's easier to judge me than to believe","time": 63},
    {"text": "gipi sumgyeotteon nalkeun saenggakdeul","time": 66},
    {"text": "gakkeum nareul jabgo gweropijiman","time": 70},
    {"text": "geureolsurok Imma shine baby","time": 73},
    {"text": "You know they ain't got a shot on me","time": 76},
    {"text": "Sunday night","time": 80},
    {"text": "I've been swallowed by my bed","time": 82},
    {"text": "I've been all over my head","time": 83},
    {"text": "Wonderin' if I gotta trying pretend","time": 85},
    {"text": "nado jal moreuneun nal","time": 88},
    {"text": "nuga arajugil gidaehaneun","time": 90},
    {"text": "nae moseubeul chajeulkka duryeoweo","time": 92},
    {"text": "jeo bichi deo balkajilsurok","time": 96},
    {"text": "nae geurimjado gireojineunde","time": 99},
    {"text": "neomu nuni bushyeool ttae","time": 102},
    {"text": "nan dwireul bol su isseulkka","time": 104},
    {"text": "on sesangi bakkwieogado","time": 107},
    {"text": "ajik naneun geudaeron geol","time": 111},
    {"text": "naega georeoganeun","time": 114},
    {"text": "i gireul kkumkkudeon","time": 116},
    {"text": "geuttae geudaero (2x)","time": 118},
    {"text": "nae maeireul chumchudeon","time": 122},
    {"text": "cheoeum geu jarie nama inneun geol","time": 125},
    {"text": "But you'll never know","time": 131.6},
    {"text": "Unless you walk in my shoes","time": 134},
    {"text": "You'll never know","time": 136},
    {"text": "eongkyeobeorin nae kkeun","time": 138},
    {"text": "'Cause everybody sees","time": 140},
    {"text": "What they wanna see","time": 142},
    {"text": "It's easier to judge me than to believe","time": 144},
    {"text": "gipi sumgyeotteon nalkeun saenggakdeul","time": 145},
    {"text": "gakkeum nareul jabgo gweropijiman","time": 147},
    {"text": "geureolsurok Imma shine baby","time": 153},
    {"text": "You know they ain't got a shot on me","time": 156},
    {"text": "garaanjeumyeon an dwae","time": 159},
    {"text": "nado jal ara","time": 162},
    {"text": "ttangman boneun chaeron nal su eopseo","time": 165},
    {"text": "gureum geonneopyeonen","time": 169},
    {"text": "ajik balkeun hae","time": 171},
    {"text": "naega geuryeowatteon geurim soge","time": 173},
    {"text": "jjijeobeorin gotteulkkaji","time": 174},
    {"text": "da biweonaego useul su itge","time": 176},
    {"text": "bogi shireotteon nawa majuhallae","time": 180},
    {"text": "nan gieokhae","time": 184.8},
    {"text": "So I'll be okay","time": 186},
    {"text": "paran nae bang hangadeuk kkochi pige","time": 188},
    {"text": "I'll always be waiting","time": 191},
    {"text": "But you'll never know","time": 195.9},
    {"text": "Unless you walk in my shoes","time": 197},
    {"text": "You'll never know","time": 199},
    {"text": "eongkyeobeorin nae kkeun","time": 201},
    {"text": "'Cause everybody sees","time": 204},
    {"text": "What they wanna see","time": 205},
    {"text": "It's easier to judge me than to believe","time": 206},
    {"text": "gipi sumgyeotteon nalkeun saenggakdeul","time": 209.5},
    {"text": "gakkeum nareul jabgo gweropijiman","time": 213},
    {"text": "geureolsurok Imma shine baby","time": 217},
    {"text": "You know they ain't got a shot on me","time": 220},
    {"text": "","time": 227}
]