[
    {"text": "Yeah, yeah, yeah, yeah"},
    {"text": "Na-na-na-na-na, na, na"},
    {"text": ""},
    {"text": "Sarangeun machi filtere sseuin geot gachi"},
    {"text": "Huimihaejyeo modeun ge pandani an dwae"},
    {"text": "Keep on struggling, struggling noryeokaedo"},
    {"text": "Bangsimhamyeon mess up, yeah"},
    {"text": "Don't know why"},
    {"text": "Swipji ana gamjeongiran geon"},
    {"text": "Jeongmal yeongwonhan geon eopseul georago"},
    {"text": "Darling, haters eonjenga tto geureoke byeonhal geol"},
    {"text": ""},
    {"text": "I'm into you"},
    {"text": "Woah-ooh-woah-ooh-woah, oh-oh-ooh-oh-oh"},
    {"text": "Gakkawojidaga"},
    {"text": "Woah-ooh-woah-ooh-woah, oh-oh-ooh-oh-oh"},
    {"text": "Tto meomchuji nan"},
    {"text": "Someday love will break up, makyeobeoryeo maebeon"},
    {"text": "Ppajyeodeuldaga tto oemyeonhae neol"},
    {"text": "Love is like a savage, mameul jinnureuji"},
    {"text": "I don't wanna mess up"},
    {"text": ""},
    {"text": "Na-nah-yeah"},
    {"text": "Everybody's gonna love somebody (Yeah)"},
    {"text": "Seollemeul ttara swipge mameul jugobatji (Yeah)"},
    {"text": "Wae ajik naege eoryeopgiman hae"},
    {"text": "Yeojeonhi dwitgeoreumchyeo nan"},
    {"text": "Na-nah-yeah"},
    {"text": "Everyday, I wanna love somebody (Yeah)"},
    {"text": "And it's okay to be a little bit selfish (Yeah)"},
    {"text": "Eonjenga jujeo eopsi"},
    {"text": "Nae mameul jugo sipeo nan"},
    {"text": ""},
    {"text": "Ijeongwaneun dareul geora mitgo sipji"},
    {"text": "I sangcheomajeo jiwojul true love (Yeah, uh)"},
    {"text": "Neon jom soljikae bwa aemaehan geon an dwae"},
    {"text": "Uisimmajeo eopge jom deo gwagamhage (deo gwagamhage)"},
    {"text": "Cliché geureon geon an dwae"},
    {"text": "Ttak hwaksineul jwo gidarilge"},
    {"text": ""},
    {"text": "I'm into you"},
    {"text": "Woah-ooh-woah-ooh-woah, oh-oh-ooh-oh-oh"},
    {"text": "Almyeonseodo wae nan"},
    {"text": "Woah-ooh-woah-ooh-woah, oh-oh-ooh-oh-oh"},
    {"text": "Tto mangseollyeojyeo"},
    {"text": "Something's gonna happen, gyeonggyehaji maebeon"},
    {"text": "Beolsseo mameul jumyeon sikge doel geol"},
    {"text": "Love is like a savage, dasi mireonaeji"},
    {"text": "I don't wanna mess up"},
    {"text": ""},
    {"text": "Na-nah-yeah"},
    {"text": "Everybody's gonna love somebody (Yeah)"},
    {"text": "Seollemeul ttara swipge mameul jugobatji (Yeah)"},
    {"text": "Wae ajik naege eoryeopgiman hae"},
    {"text": "Yeojeonhi dwitgeoreumchyeo nan"},
    {"text": "Na-nah-yeah"},
    {"text": "Everyday, I wanna love somebody (Yeah)"},
    {"text": "And it's okay to be a little bit selfish (Yeah)"},
    {"text": "Eonjenga jujeo eopsi"},
    {"text": "Nae mameul jugo sipeo nan"},
    {"text": ""},
    {"text": "Ibeonen dareugil (Ayy, ayy)"},
    {"text": "Mitgo sipeo jinsimigil bara (gil bara)"},
    {"text": "Hoksina aniramyeon (na, uh-huh)"},
    {"text": "Mwo miryeoneopsi please tell me 'Bye, bye'"},
    {"text": ""},
    {"text": "Na-nah-yeah"},
    {"text": "Everybody's gonna love somebody (Love somebody; Yeah)"},
    {"text": "Seollemeul ttara swipge mameul jugobatji (Yeah)"},
    {"text": "Wae ajik naege eoryeopgiman hae"},
    {"text": "Yeojeonhi dwitgeoreumchyeo nan"},
    {"text": "Na-nah-yeah"},
    {"text": "Everyday, I wanna love somebody"},
    {"text": "(Everyday, I wanna love somebody) (Yeah)"},
    {"text": "And it's okay to be a little bit selfish (Yeah)"},
    {"text": "Eonjenga jujeo eopsi"},
    {"text": "Nae mameul jugo sipeo nan"},
    {"text": ""}
]