[
    {"text": "Neowaui haruneun Match point"},
    {"text": "Ginjanggam soge momi an umjingnyeo"},
    {"text": "Nae mameul sumgyeo nokoseo haneun Hi-yai"},
    {"text": ""},
    {"text": "Ieojineun Rally kkeunnal jul molla"},
    {"text": "Onjongil seuchineun nunbit igeon mwolkka"},
    {"text": "Nugu hana meonjeo naseol jul molla"},
    {"text": "Hangeoreumi bujokae"},
    {"text": ""},
    {"text": "Ne mameul da heundeureo noeul geu hanmadi"},
    {"text": "Pillyohal geot gateunde"},
    {"text": ""},
    {"text": "Majuchin sungan joeun Timing"},
    {"text": "Seoneul neomeo nan Yai-yai-yai"},
    {"text": "Ijjeumeseo deonjyeobolkka"},
    {"text": "Seoneul neomeo nan Yai-yai-yai"},
    {"text": "Bwa bwa Here I go, smashing, smashing"},
    {"text": "Bwa nollaji ma (That's right)"},
    {"text": "Yai-yai-yai"},
    {"text": ""},
    {"text": "Mollatji yojeum maeiri"},
    {"text": "Jageun gongcheoreom gyesok umjingnyeo nan"},
    {"text": "Eodiro twiljin moreujiman da Fine"},
    {"text": ""},
    {"text": "Neteu seone nanwin uri saie"},
    {"text": "Nunbichi Back and forth gyesok tiki-taka"},
    {"text": "An geureon cheokaedo da badajuji"},
    {"text": "Imi sijakdoen geolkka"},
    {"text": ""},
    {"text": "Ne mame mulgyeoreul ireukil dan hanmadi"},
    {"text": "Ije junbiharyeo hae"},
    {"text": ""},
    {"text": "Majuchin sungan joeun Timing"},
    {"text": "Seoneul neomeo nan Yai-yai-yai"},
    {"text": "Ijjeumeseo deonjyeobolkka"},
    {"text": "Seoneul neomeo nan Yai-yai-yai"},
    {"text": "Bwa bwa Here I go, smashing, smashing"},
    {"text": "Bwa nollaji ma (That's right)"},
    {"text": "Yai-yai-yai"},
    {"text": ""},
    {"text": "Ireon neukkim Makes me crazy"},
    {"text": "Heotseuwinghaedo molla ama anil geoya"},
    {"text": "Gin gin geim Let me finish"},
    {"text": "Hwaksilhan ge joa"},
    {"text": ""},
    {"text": "Ireon neukkim Makes me crazy"},
    {"text": "Soni tteollyeowa"},
    {"text": "Gin gin geim Let me finish"},
    {"text": "Dabeun hanaya"},
    {"text": ""},
    {"text": "Gidarin sungan joeun Timing"},
    {"text": "Seoneul neomeo nan Yai-yai-yai"},
    {"text": "Ijjeumeseo deonjyeobolkka"},
    {"text": "Seoneul neomeo nan Yai-yai-yai"},
    {"text": "Bwa bwa Here I go, smashing, smashing"},
    {"text": "Bwa nollaji ma (That's right)"},
    {"text": "Yai-yai-yai"},
    {"text": ""}
]