[
    {"text": "Dari bichun geori wi This evening"},
    {"text": "Swieo gal teumi eomneun Fast track in my life"},
    {"text": "Sigando sigane jjotgin chae Yeah"},
    {"text": "Geeureul jureul molla So fast"},
    {"text": ""},
    {"text": "Sigyel meomchul bangbeobi isseo dan han gaji"},
    {"text": "Saljjak nun gama nan cheoncheonhi"},
    {"text": "Nege allyeojul teni"},
    {"text": ""},
    {"text": "1,"},
    {"text": "2 and maybe 7 o'clock"},
    {"text": "Neowa hamkke haneun Time sesangeun stops"},
    {"text": "When I'm with you, baby,"},
    {"text": "4,"},
    {"text": "5,"},
    {"text": "6 or 11 o'clock, hey"},
    {"text": "Kkum sok Night kkum bakkui day"},
    {"text": "Ne sunganeun nae gieok soge stop"},
    {"text": ""},
    {"text": "You make time just stop"},
    {"text": "You make time stop"},
    {"text": ""},
    {"text": "Seumulle jogagui siganeuro ieun 1 day"},
    {"text": "Ppaegokae wanbyeokae dareun geon I don't mind, yeah"},
    {"text": ""},
    {"text": "Ne miso ttoneun nunmul eorin modeun Time"},
    {"text": "Wonhae Press pause wonhae press rewind"},
    {"text": "Girl, you're shaking and breaking me urin woni doenikka"},
    {"text": "Neon naui kkeuchija naui modeun Start"},
    {"text": ""},
    {"text": "Ne 1choreul naege jullae"},
    {"text": "Deo orae hamkke halge nan Ah"},
    {"text": ""},
    {"text": "1,"},
    {"text": "2 and maybe 7 o'clock"},
    {"text": "Neowa hamkke haneunTime sesangeun Stops"},
    {"text": "When I'm with you, baby,"},
    {"text": "4,"},
    {"text": "5,"},
    {"text": "6 or 11 o'clock, hey"},
    {"text": "Kkum sok Night kkum bakkui Day"},
    {"text": "Ne sunganeun nae gieok soge Stop"},
    {"text": ""},
    {"text": "You make time just stop"},
    {"text": "You make time stop"},
    {"text": ""},
    {"text": "Ne sondeungman seuchyeodo My heart stops beating"},
    {"text": "Eonjena i sungancheoreom hamkkehan Dreaming"},
    {"text": "Kkumeuro geurin I, I jigeum uri"},
    {"text": "I, I couldn't change you even if I could, I couldn't"},
    {"text": ""},
    {"text": "Tto nae maeumeun Won't stop (Won't stop)"},
    {"text": "Eopeo moraesigye When it drops (When it drops)"},
    {"text": "Meomchwo seun Sky, yeah, I feel high"},
    {"text": "Ne 1cho,"},
    {"text": "2cho ganjikalge da"},
    {"text": ""},
    {"text": "Don't say a word sichimui bareul meomchwo seun bam"},
    {"text": "(Oh i bam) gateun kkum geu anui Fantasy"},
    {"text": "Don't say a word neul siganboda urin cheoncheonhi"},
    {"text": "(Right here next to me) sunganeul challanhi"},
    {"text": ""},
    {"text": "1,"},
    {"text": "2 and maybe 7 o'clock"},
    {"text": "Neowa hamkke haneun Time sesangeun stops"},
    {"text": "When I'm with you, baby,"},
    {"text": "4,"},
    {"text": "5,"},
    {"text": "6 or 11 o'clock, hey"},
    {"text": "Kkumsok Night kkum bakkui day"},
    {"text": "Ne sunganeun nae gieok soge Stop"},
    {"text": ""},
    {"text": "You make time just stop"},
    {"text": "You make time stop"},
    {"text": "Girl, you make time stop"},
    {"text": "Girl, you make time stop"},
    {"text": "When I'm with you baby you make time stop"},
    {"text": ""}
]