[
    {"text": "Flashing lights and we","time": 4.8},
    {"text": "Took a wrong turn and we","time": 7.97},
    {"text": "Fell down a rabbit hole","time": 10},
    {"text": "You held on tight to me","time": 15.3},
    {"text": "'Cause nothing's as it seems","time": 18.13},
    {"text": "And spinning out of control","time": 20.9},
    {"text": "Didn't they tell us don't rush into things?","time": 26},
    {"text": "Didn't you flash your green eyes at me?","time": 28.8},
    {"text": "Haven't you heard what becomes of curious minds?","time": 31.5},
    {"text": "Oh","time": 36},
    {"text": "Didn't it all seem new and exciting?","time": 36.88},
    {"text": "I felt your arms twisting around me","time": 39.2},
    {"text": "I should have slept with one eye open at night","time": 41.77},
    {"text": "We found wonderland","time": 46.88},
    {"text": "You and I got lost in it","time": 49.72},
    {"text": "And we pretended it could last forever","time": 52},
    {"text": "Eh","time": 56.5},
    {"text": "We found wonderland","time": 57.3},
    {"text": "You and I got lost in it","time": 60},
    {"text": "And life was never worse but never better","time": 62.6},
    {"text": "Eh eh","time": 67},
    {"text": "Eh eh eh eh eh","time": 68},
    {"text": "In wonderland","time": 71.9},
    {"text": "Eh eh eh eh eh","time": 73.34},
    {"text": "In wonderland","time": 76.89},
    {"text": "Eh eh eh eh eh","time": 78.4},
    {"text": "In wonderland","time": 80},
    {"text": "Eh eh eh eh eh","time": 83},
    {"text": "In wonderland","time": 86},
    {"text": "So we went on our way","time": 90.9},
    {"text": "Too in love to think straight","time": 94},
    {"text": "All alone or so it seemed","time": 96},
    {"text": "But there were strangers watching","time": 100.34},
    {"text": "And whispers turned to talking","time": 103.3},
    {"text": "And talking turned to screams","time": 106.2},
    {"text": "Oh","time": 111},
    {"text": "Didn't they tell us don't rush into things?","time": 112.2},
    {"text": "Didn't you flash your green eyes at me?","time": 114.9},
    {"text": "Didn't you calm my fears with a Cheshire cat smile?","time": 117.6},
    {"text": "Oh","time": 122},
    {"text": "Didn't it all seem new and exciting?","time": 122.7},
    {"text": "I felt your arms twisting around me","time": 125},
    {"text": "It's all fun and games 'til somebody loses their mind","time": 127.8},
    {"text": "But darling, we found wonderland","time": 132.2},
    {"text": "You and I got lost in it","time": 135.5},
    {"text": "And we pretended it could last forever","time": 137.88},
    {"text": "Eh","time": 142},
    {"text": "We found wonderland","time": 143.3},
    {"text": "You and I got lost in it","time": 145.29},
    {"text": "And life was never worse but never better","time": 148},
    {"text": "Eh e","time": 153.1},
    {"text": "Eh eh eh eh eh","time": 154.8},
    {"text": "In wonderland","time": 157.4},
    {"text": "Eh eh eh eh eh","time": 159.42},
    {"text": "In wonderland","time": 162.45},
    {"text": "Eh eh eh eh eh","time": 164.79},
    {"text": "In wonderland","time": 167.9},
    {"text": "Eh eh eh eh eh","time": 169.9},
    {"text": "In wonderland","time": 173},
    {"text": "I reached for you but you were gone","time": 177.1},
    {"text": "I knew I had to go back home","time": 182},
    {"text": "You searched the world for something else to make you feel like what we had","time": 185},
    {"text": "And in the end in wonderland we both went mad","time": 189.89},
    {"text": "Oh","time": 196.35},
    {"text": "We found wonderland","time": 198.06},
    {"text": "You and I got lost in it","time": 200.23},
    {"text": "And we pretended it could last forever (last forever)","time": 203},
    {"text": "Eh eh","time": 207.9},
    {"text": "We found wonderland","time": 208.6},
    {"text": "You and I got lost in it (got lost in it)","time": 211},
    {"text": "And life was never worse but never better (never better)","time": 213.23},
    {"text": "Eh eh","time": 218.4},
    {"text": "We found wonderland","time": 219.25},
    {"text": "You and I got lost in it (wonderland)","time": 221.9},
    {"text": "And we pretended it could last forever (in wonderland)","time": 224.1},
    {"text": "We found wonderland","time": 229.2},
    {"text": "You and I got lost in it (wonderland)","time": 231.9},
    {"text": "And life was never worse but never better","time": 234.8},
    {"text": "In wonderland","time": 238},
    {"text": "","time": 242.1},
    {"text": "","time": 242.6}
]