[
    {"text": "Don't look away 'cause"},
    {"text": "I'ma zoom in on ya"},
    {"text": ""},
    {"text": "You know I'm not afraid to go"},
    {"text": "Jump straight into the storm"},
    {"text": "Sit back, enjoy the ride (Ok, ok)"},
    {"text": "I don't care what they say"},
    {"text": "I want it all for me"},
    {"text": "Can't stop me"},
    {"text": "Let 'em all know that"},
    {"text": "I'm ready to take it on"},
    {"text": ""},
    {"text": "We can be extraordinary"},
    {"text": "Or maybe you're ok with just ordinary?"},
    {"text": "Huh?"},
    {"text": "This could be the end of me"},
    {"text": "So I'ma bring you closer like my enemy"},
    {"text": "BOOM"},
    {"text": "Talk that talk yeah all you wanna"},
    {"text": "Walking through together"},
    {"text": "Show you what I got"},
    {"text": "Extreme me"},
    {"text": "That's just what I like"},
    {"text": ""},
    {"text": "Keeping it simple just for ya"},
    {"text": "All you gotta do is just try it"},
    {"text": "Don't even fight it"},
    {"text": "This fate ain't for you to resist"},
    {"text": "Don't look away, let me show ya"},
    {"text": "Winning while I'm smiling"},
    {"text": "Zoomin' in, zoomin' in on ya"},
    {"text": ""},
    {"text": "Zoom zoomin'"},
    {"text": "I'ma zoom, zoom in on ya"},
    {"text": "I'ma zoom in on ya"},
    {"text": "Zoom zoomin'"},
    {"text": "I'ma zoom, zoom in on ya"},
    {"text": "I'ma zoom in on ya"},
    {"text": "Zoom zoomin'"},
    {"text": "I'ma zoom, zoom in on ya"},
    {"text": "I'ma zoom in on ya"},
    {"text": "Zoom zoom"},
    {"text": "Time to have some fun"},
    {"text": "Zoom zoom"},
    {"text": "Ready? Here we go"},
    {"text": ""},
    {"text": "Take it higher"},
    {"text": "Yabai supīdo de"},
    {"text": "Mabataki sae dangerous? yes"},
    {"text": "Giving you, giving you all I got"},
    {"text": "Sokudo agete ikou yo"},
    {"text": "ZOOM ZOOM"},
    {"text": "Everybody knows I'm extra"},
    {"text": "BOOM BOOM"},
    {"text": "XTreme in my ways"},
    {"text": "Down, down going 1,"},
    {"text": "2,"},
    {"text": "3"},
    {"text": "Sugu ni miseteageru"},
    {"text": "Hora A to Z"},
    {"text": "Hey!"},
    {"text": ""},
    {"text": "Kimi to tachiagaru tatakai ni mukau"},
    {"text": "Yuzurenai omoi o mamoru tame"},
    {"text": "Hitomi sorasanaide"},
    {"text": "Tsugi no sekai e"},
    {"text": "Zoomin' in, zoomin' in on ya"},
    {"text": ""},
    {"text": "Zoom zoomin'"},
    {"text": "I'ma zoom, zoom in on ya"},
    {"text": "I'ma zoom in on ya"},
    {"text": "Zoom zoomin'"},
    {"text": "I'ma zoom, zoom in on ya"},
    {"text": "Ima zoom in on ya"},
    {"text": "Zoom zoomin'"},
    {"text": "I'ma zoom, zoom in on ya"},
    {"text": "I'ma zoom in on ya"},
    {"text": "Zoom zoom"},
    {"text": "Tanoshimou yo"},
    {"text": "Zoom zoom"},
    {"text": "Kono shunkan o"},
    {"text": ""},
    {"text": "Ima hajimaru"},
    {"text": "Kono sutēji de kagayaku yo shining bright"},
    {"text": "Tomerarenai tomara senai"},
    {"text": "Come bring the encore yeah"},
    {"text": ""},
    {"text": "Yeah"},
    {"text": "Zoomin' zoomin'"},
    {"text": "I'ma zoom in on ya"},
    {"text": "Yeah"},
    {"text": "I'ma zoom, zoom in on ya"},
    {"text": ""},
    {"text": "Zoom zoomin'"},
    {"text": "I'ma zoom, zoom in on ya"},
    {"text": "I'ma zoom in on ya"},
    {"text": "Zoom zoomin'"},
    {"text": "I'ma zoom, zoom in on ya"},
    {"text": "Ima zoom in on ya"},
    {"text": "Zoom zoomin'"},
    {"text": "I'ma zoom, zoom in on ya"},
    {"text": "I'ma zoom in on ya"},
    {"text": "Zoom zoom"},
    {"text": "Tanoshimou yo"},
    {"text": "Zoom zoom"},
    {"text": "Kono shunkan o"},
    {"text": ""},
    {"text": "Now ya in my sights"},
    {"text": "I can't leave you behind"},
    {"text": "You know I'm doing it my way"},
    {"text": "'Cause I'm zoom, zoomin'"},
    {"text": "I'ma zoom in on ya"},
    {"text": "Now ya in my sights"},
    {"text": "I can't leave you behind"},
    {"text": "I'm gonna take it to the top"},
    {"text": "'Cause I'm zoom, zoomin'"},
    {"text": "I'ma zoom in on ya"},
    {"text": ""}
]